CHANGELOG.md
pycounts_ajz/__init__.py
pycounts_ajz/data/__init__.py
pycounts_ajz/data/flatland.txt
pycounts_ajz/datasets.py
pycounts_ajz/plotting.py
pycounts_ajz/pycounts.py
tests/einstein.txt
tests/test_pycounts.py
pycounts_ajz-0.2.0.dist-info/LICENSE
pycounts_ajz-0.2.0.dist-info/METADATA
pycounts_ajz-0.2.0.dist-info/WHEEL
pycounts_ajz-0.2.0.dist-info/RECORD
